ipc_py_objects/__init__.py
ipc_py_objects/versions/__init__.py
ipc_py_objects/versions/v_0/__init__.py
ipc_py_objects/versions/v_1/__init__.py
interprocesspyobjects-1.0.7.dist-info/METADATA
interprocesspyobjects-1.0.7.dist-info/WHEEL
interprocesspyobjects-1.0.7.dist-info/licenses/LICENSE.md
interprocesspyobjects-1.0.7.dist-info/licenses/NOTICE
interprocesspyobjects-1.0.7.dist-info/RECORD
